kuay/__init__.py
kuay/cli/__init__.py
kuay/cli/main.py
kuay/graphql/__init__.py
kuay/graphql/queries/__init__.py
kuay/graphql/queries/whale.py
kuay/schema.py
kuay/ward.py
kuay-0.1.19.dist-info/entry_points.txt
kuay-0.1.19.dist-info/WHEEL
kuay-0.1.19.dist-info/METADATA
kuay-0.1.19.dist-info/RECORD
