Metadata-Version: 2.1
Name: kuay
Version: 0.1.19
Summary: 
Author: jhnnsrs
Author-email: jhnnsrs@gmail.com
Requires-Python: >=3.8,<4.0
Classifier: Programming Language :: Python :: 3
Classifier: Programming Language :: Python :: 3.10
Classifier: Programming Language :: Python :: 3.8
Classifier: Programming Language :: Python :: 3.9
Requires-Dist: herre (>=0.1.55,<0.2.0)
